{
  "total": 5,
  "yakuman_count": 4,
  "sanbaiman_count": 1,
  "games": [
    {
      "date": "2025-12-07_022208_RinshanNomi.json",
      "filename": "2025-12-07_022208_RinshanNomi.json",
      "round": "南三局",
      "round_idx": 9,
      "winner": "加賀百万石",
      "point_desc": "Kazoe Yakuman 6000-12000点",
      "yaku": "Fully Concealed Hand(1飜), Riichi(1飜), Ippatsu(1飜), Dora(5飜), Red Five(1飜), Ura Dora(4飜)",
      "yaku_list": [
        "Fully Concealed Hand(1飜)",
        "Riichi(1飜)",
        "Ippatsu(1飜)",
        "Dora(5飜)",
        "Red Five(1飜)",
        "Ura Dora(4飜)"
      ],
      "is_tsumo": true,
      "title_suffix": "加賀百万石的役满自摸",
      "tenhou_url": "https://tenhou.net/5/#json={\"title\":[\"Santi League -- M League Rule\",\"加賀百万石的役满自摸\"],\"name\":[\"南美雀后\",\"santi\",\"RinshanNomi\",\"加賀百万石\"],\"rule\":{\"disp\":\"M League Rule\",\"aka53\":1,\"aka52\":1,\"aka51\":1},\"log\":[[[6,0,0],[30700,35200,25900,8200],[14,34],[27,14],[16,36,45,33,21,43,19,21,16,28,36,22,23],[11,39,38,37,25,27,32,17],[45,60,19,33,28,11,21,32],[12,45,45,39,38,28,44,44,24,36,19,22,11],[\"4545p45\",13,\"44p4444\",35,33,17,11,26,11,12],[19,39,28,38,60,60,60,60,60,11],[37,34,42,13,12,46,28,24,23,39,27,45,24],[41,31,31,23,31,33,38,44,\"c262728\",18,26],[45,60,60,42,60,46,41,60,12,13,38],[37,51,37,29,47,31,35,34,22,36,15,28,15],[44,14,26,15,32,23,38,46,25,21,27],[47,44,31,29,60,14,\"511515a15\",60,28,\"r38\"],[\"和了\",[-6000,-6000,-12000,25000],[3,3,3,\"Kazoe Yakuman 6000-12000点\",\"門前清自摸和(1飜)\",\"立直(1飜)\",\"一発(1飜)\",\"ドラ(5飜)\",\"赤ドラ(1飜)\",\"裏ドラ(4飜)\"]]]]}",
      "type": "yakuman"
    },
    {
      "date": "2025-11-13_205915_姫野婭也.json",
      "filename": "2025-11-13_205915_姫野婭也.json",
      "round": "南四局",
      "round_idx": 9,
      "winner": "姫野婭也",
      "point_desc": "Yakuman 48000点",
      "yaku": "Thirteen Orphans(役満)",
      "yaku_list": [
        "Thirteen Orphans(役満)"
      ],
      "is_tsumo": false,
      "title_suffix": "姫野婭也的国士无双役满荣和",
      "tenhou_url": "https://tenhou.net/5/#json={\"title\":[\"Santi League -- M League Rule\",\"姫野婭也的国士无双役满荣和\"],\"name\":[\"阿佳丶\",\"santi\",\"Vermilio\",\"姫野婭也\"],\"rule\":{\"disp\":\"M League Rule\",\"aka53\":1,\"aka52\":1,\"aka51\":1},\"log\":[[[7,0,0],[6100,34200,9600,50100],[26],[],[33,45,26,43,47,34,24,22,32,15,26,46,24],[36,42,39,13,37,53,16,12,46,33,45],[43,47,60,45,46,42,13,60,60,60,60],[14,12,22,52,18,14,41,29,12,14,44,47,36],[28,23,17,42,44,23,38,13,29,13,23],[41,44,47,60,60,36,60,28,13,60,22],[32,24,17,27,27,38,34,42,39,18,34,28,21],[11,47,33,18,24,38,\"2727p27\",17,11,31,31,29],[21,60,11,42,38,60,28,34,60,60,60,60],[21,39,25,16,46,22,19,43,31,47,45,33,41],[44,11,13,27,35,31,42,27,16,37,14,36],[16,22,60,33,60,25,27,60,60,60,60,60],[\"和了\",[0,0,-48000,48000],[3,2,3,\"役満 48000点\",\"国士無双(役満)\"]]]]}",
      "type": "yakuman"
    },
    {
      "date": "2025-10-15_002503_小地鼠爱点炮.json",
      "filename": "2025-10-15_002503_小地鼠爱点炮.json",
      "round": "南四局",
      "round_idx": 9,
      "winner": "小地鼠爱点炮",
      "point_desc": "Sanbaiman 12000点∀",
      "yaku": "Twice Pure Double Sequence(3飜), All Simples(1飜), Fully Concealed Hand(1飜), Pinfu(1飜), Riichi(1飜), Ippatsu(1飜), Red Five(2飜), Ura Dora(2飜)",
      "yaku_list": [
        "Twice Pure Double Sequence(3飜)",
        "All Simples(1飜)",
        "Fully Concealed Hand(1飜)",
        "Pinfu(1飜)",
        "Riichi(1飜)",
        "Ippatsu(1飜)",
        "Red Five(2飜)",
        "Ura Dora(2飜)"
      ],
      "is_tsumo": true,
      "title_suffix": "小地鼠爱点炮的三倍满自摸",
      "tenhou_url": "https://tenhou.net/5/#json={\"title\":[\"Santi League -- M League Rule\",\"小地鼠爱点炮的三倍满自摸\"],\"name\":[\"santi\",\"南美雀后\",\"姫野婭也\",\"小地鼠爱点炮\"],\"rule\":{\"disp\":\"M League Rule\",\"aka53\":1,\"aka52\":1,\"aka51\":1},\"log\":[[[7,0,0],[36700,3200,53600,6500],[28],[13],[41,37,19,28,26,47,33,42,19,14,16,22,31],[41,22,12,45,36,26,16,22],[47,37,33,26,28,60,14,36],[23,44,23,45,32,11,17,16,44,18,47,33,42],[24,41,39,11,18,24,11,46],[42,60,60,47,45,33,32,44],[25,36,37,35,18,25,28,42,15,47,43,53,24],[21,12,24,38,37,36,34,29],[60,43,47,28,18,12,15,60],[39,51,31,26,27,43,36,14,27,14,13,29,27],[25,33,27,44,15,38,52,26,13],[39,43,36,60,33,60,31,\"r29\"],[\"和了\",[-12000,-12000,-12000,37000],[3,3,3,\"三倍満 12000点∀\",\"二盃口(3飜)\",\"断幺九(1飜)\",\"門前清自摸和(1飜)\",\"平和(1飜)\",\"立直(1飜)\",\"一発(1飜)\",\"赤ドラ(2飜)\",\"裏ドラ(2飜)\"]]]]}",
      "type": "sanbaiman"
    },
    {
      "date": "2025-09-22_221238_小地鼠爱点炮.json",
      "filename": "2025-09-22_221238_小地鼠爱点炮.json",
      "round": "南二局3本场",
      "round_idx": 14,
      "winner": "姫野婭也",
      "point_desc": "Yakuman 32000点",
      "yaku": "Thirteen Orphans(役満)",
      "yaku_list": [
        "Thirteen Orphans(役満)"
      ],
      "is_tsumo": false,
      "title_suffix": "姫野婭也的国士无双役满荣和",
      "tenhou_url": "https://tenhou.net/5/#json={\"title\":[\"Santi League -- M League Rule\",\"姫野婭也的国士无双役满荣和\"],\"name\":[\"南美雀后\",\"小地鼠爱点炮\",\"姫野婭也\",\"DreamKQ\"],\"rule\":{\"disp\":\"M League Rule\",\"aka53\":1,\"aka52\":1,\"aka51\":1},\"log\":[[[5,3,0],[33700,46200,-15200,35300],[42],[],[23,16,18,18,44,23,14,45,42,33,35,24,26],[14,37,31,18,39,41,22,19,43],[42,45,44,26,31,60,39,60,60],[12,41,23,17,43,27,52,22,14,22,36,25,46],[38,19,45,33,25,47,15,11,32,46],[43,46,60,41,27,60,33,60,60,60],[41,24,43,38,45,19,34,11,47,12,26,16,44],[21,46,12,53,29,13,19,36,39,31],[38,34,16,26,53,24,13,12,12,36],[47,35,27,47,31,39,37,11,51,39,13,24,35],[37,26,45,28,24,27,33,21,23,42],[31,24,60,11,60,26,60,60,13,60],[\"和了\",[0,0,32900,-32900],[2,3,2,\"役満 32000点\",\"国士無双(役満)\"]]]]}",
      "type": "yakuman"
    },
    {
      "date": "2025-08-03_024601_santi.json",
      "filename": "2025-08-03_024601_santi.json",
      "round": "东一局2本场",
      "round_idx": 2,
      "winner": "santi",
      "point_desc": "Yakuman 8000-16000点",
      "yaku": "Four Concealed Triplets(役満)",
      "yaku_list": [
        "Four Concealed Triplets(役満)"
      ],
      "is_tsumo": true,
      "title_suffix": "santi的四暗刻役满自摸",
      "tenhou_url": "https://tenhou.net/5/#json={\"title\":[\"Santi League -- M League Rule\",\"santi的四暗刻役满自摸\"],\"name\":[\"mkcu\",\"RinshanNomi\",\"姫野婭也\",\"santi\"],\"rule\":{\"disp\":\"M League Rule\",\"aka53\":1,\"aka52\":1,\"aka51\":1},\"log\":[[[0,2,0],[34600,20800,23800,20800],[45],[34],[14,11,19,46,16,39,38,36,21,27,32,36,18],[22,25,12,42,32,23,22,34,38,25,12,14,31],[11,32,19,60,60,46,60,39,12,18,14,12,60],[47,18,29,39,31,37,38,45,51,33,34,53,16],[32,25,34,18,47,19,15,41,32,18,38,26],[29,45,47,25,34,60,47,60,15,\"r31\",60,60],[23,16,46,47,37,29,31,46,11,33,21,29,26],[12,12,19,17,29,\"46p4646\",24,43,13,22,36,11,11],[16,60,26,47,37,17,19,60,24,29,29,29,36],[44,41,42,15,41,42,41,27,35,47,28,39,45],[27,35,35,23,28,45,13,14,28,33,24,52,27],[39,45,47,60,15,60,60,60,\"r44\",60,60,60],[\"和了\",[-16200,-8200,-8200,34600],[3,3,3,\"役満 8000-16000点\",\"四暗刻(役満)\"]]]]}",
      "type": "yakuman"
    }
  ]
}